<annotation>
	<folder>sortedimages</folder>
	<filename>trafficlight0207.jpg</filename>
	<path>C:/Users/ashtamypc/Desktop/PYTHON/3.12.18/coverted/sortedimages/trafficlight0207.jpg</path>
	<source>
		<database>Unknown</database>
	</source>
	<size>
		<width>1600</width>
		<height>900</height>
		<depth>3</depth>
	</size>
	<segmented>0</segmented>
	<object>
		<name>trafficlight</name>
		<pose>Unspecified</pose>
		<truncated>0</truncated>
		<difficult>0</difficult>
		<bndbox>
			<xmin>1173</xmin>
			<ymin>71</ymin>
			<xmax>1214</xmax>
			<ymax>160</ymax>
		</bndbox>
	</object>
	<object>
		<name>trafficlight</name>
		<pose>Unspecified</pose>
		<truncated>0</truncated>
		<difficult>0</difficult>
		<bndbox>
			<xmin>1272</xmin>
			<ymin>67</ymin>
			<xmax>1315</xmax>
			<ymax>161</ymax>
		</bndbox>
	</object>
	<object>
		<name>trafficlight</name>
		<pose>Unspecified</pose>
		<truncated>0</truncated>
		<difficult>0</difficult>
		<bndbox>
			<xmin>1396</xmin>
			<ymin>56</ymin>
			<xmax>1444</xmax>
			<ymax>147</ymax>
		</bndbox>
	</object>
</annotation>
