<annotation>
	<folder>sortedimages</folder>
	<filename>trafficlight0060.jpg</filename>
	<path>C:/Users/ashtamypc/Desktop/PYTHON/3.12.18/coverted/sortedimages/trafficlight0060.jpg</path>
	<source>
		<database>Unknown</database>
	</source>
	<size>
		<width>825</width>
		<height>486</height>
		<depth>3</depth>
	</size>
	<segmented>0</segmented>
	<object>
		<name>trafficlight</name>
		<pose>Unspecified</pose>
		<truncated>0</truncated>
		<difficult>0</difficult>
		<bndbox>
			<xmin>433</xmin>
			<ymin>142</ymin>
			<xmax>453</xmax>
			<ymax>186</ymax>
		</bndbox>
	</object>
	<object>
		<name>trafficlight</name>
		<pose>Unspecified</pose>
		<truncated>0</truncated>
		<difficult>0</difficult>
		<bndbox>
			<xmin>775</xmin>
			<ymin>95</ymin>
			<xmax>802</xmax>
			<ymax>162</ymax>
		</bndbox>
	</object>
</annotation>
